simple_calulator_by_mk/__init__.py
simple_calulator_by_mk/catculator.py
simple_calulator_by_mk-0.1.2.dist-info/LICENSE
simple_calulator_by_mk-0.1.2.dist-info/METADATA
simple_calulator_by_mk-0.1.2.dist-info/WHEEL
simple_calulator_by_mk-0.1.2.dist-info/top_level.txt
simple_calulator_by_mk-0.1.2.dist-info/RECORD
